AgileP/__init__.py
AgileP/central.py
AgileP/rule.py
AgileP/model/__init__.py
AgileP/model/basic.py
AgileP/model/extension.py
AgileP/model/validate.py
AgileP-1.0.0.dist-info/LICENSE.txt
AgileP-1.0.0.dist-info/METADATA
AgileP-1.0.0.dist-info/WHEEL
AgileP-1.0.0.dist-info/top_level.txt
AgileP-1.0.0.dist-info/RECORD
