Metadata-Version: 2.1
Name: AgileP
Version: 1.0.0
Summary: Python parametric check tools
Home-page: https://github.com/rexyan/AgileP
Author: Rex
Author-email: rex_yan@126.com
License: MIT
Platform: UNKNOWN
Classifier: Development Status :: 4 - Beta
Classifier: Intended Audience :: Developers
Classifier: Topic :: Software Development :: Build Tools
Classifier: License :: OSI Approved :: MIT License
Classifier: Programming Language :: Python
Classifier: Programming Language :: Python :: 3.5
Classifier: Programming Language :: Python :: 3.6
Classifier: Programming Language :: Python :: 3.7
